ally_ai_core/__init__.py
ally_ai_core/utils.py
ally_ai_core/context_managers/__init__.py
ally_ai_core/context_managers/logged_step.py
ally_ai_core/decorators/__init__.py
ally_ai_core/decorators/timed.py
ally_ai_core/decorators/trace.py
ally_ai_core/errors/YamlParseError.py
ally_ai_core/errors/__init__.py
ally_ai_core/settings/Settings.py
ally_ai_core/settings/__init__.py
ally_ai_core-0.7.0.dist-info/LICENSE
ally_ai_core-0.7.0.dist-info/METADATA
ally_ai_core-0.7.0.dist-info/WHEEL
ally_ai_core-0.7.0.dist-info/top_level.txt
ally_ai_core-0.7.0.dist-info/RECORD
